keyauth/__init__.py
keyauth/api.py
keyauth/classes.py
keyauth/encryption.py
keyauth/exceptions.py
keyauth/misc.py
keyauth-1.0.3.dist-info/METADATA
keyauth-1.0.3.dist-info/WHEEL
keyauth-1.0.3.dist-info/top_level.txt
keyauth-1.0.3.dist-info/RECORD
