Metadata-Version: 2.1
Name: keyauth
Version: 1.0.3
Summary: Keyauth.win API Wrapper for python3
Home-page: https://github.com/dropout1337
Author: dropout
Author-email: dropout@fbi.ac
License: UNKNOWN
Platform: UNKNOWN
Classifier: Development Status :: 5 - Production/Stable
Classifier: License :: OSI Approved :: MIT License
Classifier: Intended Audience :: Developers
Classifier: Natural Language :: English
Classifier: Operating System :: OS Independent
Classifier: Programming Language :: Python :: 3.8
Classifier: Programming Language :: Python :: 3.9
Classifier: Topic :: Internet
Classifier: Topic :: Software Development :: Libraries
Classifier: Topic :: Software Development :: Libraries :: Python Modules
Classifier: Topic :: Utilities
Requires-Dist: requests
Requires-Dist: pywin32
Requires-Dist: pycryptodome
